homu/utils.py
homu/main.py
homu/server.py
homu/html/queue.html
homu/html/index.html
homu-0.2.0.dist-info/DESCRIPTION.rst
homu-0.2.0.dist-info/top_level.txt
homu-0.2.0.dist-info/METADATA
homu-0.2.0.dist-info/WHEEL
homu-0.2.0.dist-info/entry_points.txt
homu-0.2.0.dist-info/RECORD
homu-0.2.0.dist-info/metadata.json
