Metadata-Version: 2.0
Name: homu
Version: 0.2.0
Summary: A bot that integrates with GitHub and your favorite continuous integration service
Home-page: https://github.com/barosl/homu
Author: Barosl Lee
Author-email: UNKNOWN
License: UNKNOWN
Platform: UNKNOWN
Requires-Dist: github3.py
Requires-Dist: toml
Requires-Dist: Jinja2
Requires-Dist: requests
Requires-Dist: bottle
Requires-Dist: waitress
